promoter_calculator/__init__.py
promoter_calculator/cli.py
promoter_calculator/free_energy_coeffs.npy
promoter_calculator/model_intercept.npy
promoter_calculator/original.py
promoter_calculator/promoter_calculator.py
promoter_calculator/util.py
promoter_calculator/wrapper.py
promotercalculator-1.2.4.dist-info/LICENSE
promotercalculator-1.2.4.dist-info/METADATA
promotercalculator-1.2.4.dist-info/WHEEL
promotercalculator-1.2.4.dist-info/entry_points.txt
promotercalculator-1.2.4.dist-info/top_level.txt
promotercalculator-1.2.4.dist-info/RECORD
